<Properties StartupConfiguration="{649CB10D-8BF9-3A6D-B5FA-01E547A7015C}|">
  <MonoDevelop.Ide.Workbench ActiveDocument="Assets/Zoombie/zoombieScript.cs">
    <Files>
      <File FileName="Assets/killer/KillerSCript.cs" Line="1" Column="1" />
      <File FileName="Assets/Player/PlayerController.cs" Line="13" Column="1" />
      <File FileName="Assets/zoombie.cs" Line="54" Column="1" />
      <File FileName="Assets/zoombieScript.cs" Line="1" Column="1" />
    </Files>
    <Pads>
      <Pad Id="ProjectPad">
        <State name="__root__">
          <Node name="3D model" expanded="True">
            <Node name="Assets" expanded="True">
              <Node name="killer" expanded="True" />
              <Node name="Player" expanded="True" />
              <Node name="Zoombie" expanded="True">
                <Node name="zoombieScript.cs" selected="True" />
              </Node>
            </Node>
          </Node>
        </State>
      </Pad>
    </Pads>
  </MonoDevelop.Ide.Workbench>
  <MonoDevelop.Ide.DebuggingService.PinnedWatches />
  <MonoDevelop.Ide.Workspace ActiveConfiguration="Debug" />
  <MonoDevelop.Ide.ItemProperties.Assembly-CSharp PreferredExecutionTarget="9fc6ebbd-08ea-4f85-a3d8-0da9d5ad466c" />
  <MonoDevelop.Ide.DebuggingService.Breakpoints>
    <BreakpointStore />
  </MonoDevelop.Ide.DebuggingService.Breakpoints>
  <MultiItemStartupConfigurations />
</Properties>